inkbunny/__init__.py
inkbunny/api.py
inkbunny-0.0.3.dist-info/LICENSE
inkbunny-0.0.3.dist-info/METADATA
inkbunny-0.0.3.dist-info/WHEEL
inkbunny-0.0.3.dist-info/top_level.txt
inkbunny-0.0.3.dist-info/RECORD
